[
{"time": {"hour": 23, "minute": 58, "second": 1}, "price": 5793.99463504},
{"time": {"hour": 23, "minute": 55, "second": 2}, "price": 5795.1407169},
{"time": {"hour": 23, "minute": 53, "second": 2}, "price": 5791.28869546},
{"time": {"hour": 23, "minute": 50, "second": 2}, "price": 5790.18397677},
{"time": {"hour": 23, "minute": 48, "second": 2}, "price": 5787.49043988},
{"time": {"hour": 23, "minute": 45, "second": 1}, "price": 5786.14388046},
{"time": {"hour": 23, "minute": 43, "second": 1}, "price": 5781.90721326},
{"time": {"hour": 23, "minute": 40, "second": 1}, "price": 5781.18204025},
{"time": {"hour": 23, "minute": 38, "second": 2}, "price": 5779.99977816},
{"time": {"hour": 23, "minute": 35, "second": 2}, "price": 5779.39412808},
{"time": {"hour": 23, "minute": 33, "second": 2}, "price": 5778.39638973},
{"time": {"hour": 23, "minute": 30, "second": 1}, "price": 5779.70531719},
{"time": {"hour": 23, "minute": 27, "second": 1}, "price": 5782.39953084},
{"time": {"hour": 23, "minute": 25, "second": 1}, "price": 5784.73102387},
{"time": {"hour": 23, "minute": 22, "second": 3}, "price": 5784.19848231},
{"time": {"hour": 23, "minute": 20, "second": 1}, "price": 5788.69144925},
{"time": {"hour": 23, "minute": 17, "second": 2}, "price": 5790.11020356},
{"time": {"hour": 23, "minute": 15, "second": 2}, "price": 5791.92189065},
{"time": {"hour": 23, "minute": 12, "second": 1}, "price": 5789.78166924},
{"time": {"hour": 23, "minute": 10, "second": 1}, "price": 5787.60557021},
{"time": {"hour": 23, "minute": 7, "second": 1}, "price": 5790.02708495},
{"time": {"hour": 23, "minute": 5, "second": 2}, "price": 5790.32950267},
{"time": {"hour": 23, "minute": 2, "second": 1}, "price": 5792.27569818},
{"time": {"hour": 23, "minute": 0, "second": 1}, "price": 5794.9285452},
{"time": {"hour": 22, "minute": 57, "second": 1}, "price": 5796.87730399},
{"time": {"hour": 22, "minute": 55, "second": 1}, "price": 5796.03619355},
{"time": {"hour": 22, "minute": 52, "second": 2}, "price": 5796.73708382},
{"time": {"hour": 22, "minute": 49, "second": 2}, "price": 5796.75261794},
{"time": {"hour": 22, "minute": 47, "second": 6}, "price": 5792.29764966},
{"time": {"hour": 22, "minute": 44, "second": 2}, "price": 5793.86726951},
{"time": {"hour": 22, "minute": 42, "second": 2}, "price": 5792.51736246},
{"time": {"hour": 22, "minute": 39, "second": 1}, "price": 5797.61165751},
{"time": {"hour": 22, "minute": 37, "second": 1}, "price": 5798.86688814},
{"time": {"hour": 22, "minute": 34, "second": 2}, "price": 5799.70129592},
{"time": {"hour": 22, "minute": 32, "second": 1}, "price": 5800.26142455},
{"time": {"hour": 22, "minute": 29, "second": 2}, "price": 5801.95636156},
{"time": {"hour": 22, "minute": 27, "second": 2}, "price": 5802.06623627},
{"time": {"hour": 22, "minute": 24, "second": 1}, "price": 5801.26524046},
{"time": {"hour": 22, "minute": 22, "second": 1}, "price": 5787.40304829},
{"time": {"hour": 22, "minute": 19, "second": 3}, "price": 5783.70835829},
{"time": {"hour": 22, "minute": 17, "second": 2}, "price": 5781.66147738},
{"time": {"hour": 22, "minute": 14, "second": 1}, "price": 5778.80725667},
{"time": {"hour": 22, "minute": 11, "second": 2}, "price": 5778.21809769},
{"time": {"hour": 22, "minute": 9, "second": 1}, "price": 5778.35874754},
{"time": {"hour": 22, "minute": 6, "second": 2}, "price": 5777.90231843},
{"time": {"hour": 22, "minute": 4, "second": 2}, "price": 5777.79774368},
{"time": {"hour": 22, "minute": 1, "second": 1}, "price": 5778.96918133},
{"time": {"hour": 21, "minute": 59, "second": 1}, "price": 5780.63672129},
{"time": {"hour": 21, "minute": 56, "second": 1}, "price": 5781.68363795},
{"time": {"hour": 21, "minute": 54, "second": 1}, "price": 5779.23911908},
{"time": {"hour": 21, "minute": 51, "second": 1}, "price": 5778.69328351},
{"time": {"hour": 21, "minute": 49, "second": 2}, "price": 5776.6243745},
{"time": {"hour": 21, "minute": 46, "second": 1}, "price": 5779.3508067},
{"time": {"hour": 21, "minute": 44, "second": 1}, "price": 5775.72567082},
{"time": {"hour": 21, "minute": 41, "second": 1}, "price": 5777.14694801},
{"time": {"hour": 21, "minute": 39, "second": 2}, "price": 5779.87785058},
{"time": {"hour": 21, "minute": 36, "second": 3}, "price": 5782.17292117},
{"time": {"hour": 21, "minute": 33, "second": 2}, "price": 5779.02637612},
{"time": {"hour": 21, "minute": 31, "second": 2}, "price": 5776.69877995},
{"time": {"hour": 21, "minute": 28, "second": 2}, "price": 5775.77290474},
{"time": {"hour": 21, "minute": 26, "second": 2}, "price": 5773.92399912},
{"time": {"hour": 21, "minute": 23, "second": 4}, "price": 5774.42747895},
{"time": {"hour": 21, "minute": 21, "second": 1}, "price": 5777.15153988},
{"time": {"hour": 21, "minute": 18, "second": 2}, "price": 5778.18453506},
{"time": {"hour": 21, "minute": 16, "second": 2}, "price": 5780.96823568},
{"time": {"hour": 21, "minute": 13, "second": 2}, "price": 5783.4522474},
{"time": {"hour": 21, "minute": 11, "second": 1}, "price": 5787.45050551},
{"time": {"hour": 21, "minute": 8, "second": 2}, "price": 5791.20564119},
{"time": {"hour": 21, "minute": 6, "second": 2}, "price": 5787.75082347},
{"time": {"hour": 21, "minute": 3, "second": 1}, "price": 5786.83084695},
{"time": {"hour": 21, "minute": 0, "second": 3}, "price": 5783.00726791},
{"time": {"hour": 20, "minute": 58, "second": 1}, "price": 5778.03768364},
{"time": {"hour": 20, "minute": 55, "second": 2}, "price": 5774.77552795},
{"time": {"hour": 20, "minute": 53, "second": 1}, "price": 5771.38806521},
{"time": {"hour": 20, "minute": 50, "second": 2}, "price": 5767.7557012},
{"time": {"hour": 20, "minute": 48, "second": 5}, "price": 5762.15970344},
{"time": {"hour": 20, "minute": 45, "second": 1}, "price": 5759.21575886},
{"time": {"hour": 20, "minute": 43, "second": 1}, "price": 5760.28122936},
{"time": {"hour": 20, "minute": 40, "second": 2}, "price": 5758.84042308},
{"time": {"hour": 20, "minute": 38, "second": 2}, "price": 5756.91085941},
{"time": {"hour": 20, "minute": 35, "second": 1}, "price": 5757.34372916},
{"time": {"hour": 20, "minute": 33, "second": 1}, "price": 5757.04024313},
{"time": {"hour": 20, "minute": 30, "second": 1}, "price": 5760.57254145},
{"time": {"hour": 20, "minute": 28, "second": 1}, "price": 5761.69738487},
{"time": {"hour": 20, "minute": 25, "second": 2}, "price": 5761.95688385},
{"time": {"hour": 20, "minute": 22, "second": 1}, "price": 5756.49743488},
{"time": {"hour": 20, "minute": 20, "second": 1}, "price": 5755.92835024},
{"time": {"hour": 20, "minute": 17, "second": 1}, "price": 5755.77553414},
{"time": {"hour": 20, "minute": 15, "second": 1}, "price": 5759.1867107},
{"time": {"hour": 20, "minute": 12, "second": 1}, "price": 5761.57961238},
{"time": {"hour": 20, "minute": 10, "second": 1}, "price": 5760.82528581},
{"time": {"hour": 20, "minute": 7, "second": 2}, "price": 5760.83910743},
{"time": {"hour": 20, "minute": 5, "second": 2}, "price": 5758.21403266},
{"time": {"hour": 20, "minute": 2, "second": 3}, "price": 5752.73519067},
{"time": {"hour": 20, "minute": 0, "second": 2}, "price": 5753.9320959},
{"time": {"hour": 19, "minute": 57, "second": 1}, "price": 5751.98863977},
{"time": {"hour": 19, "minute": 55, "second": 2}, "price": 5753.19126852},
{"time": {"hour": 19, "minute": 52, "second": 1}, "price": 5753.3817545},
{"time": {"hour": 19, "minute": 49, "second": 2}, "price": 5757.72204879},
{"time": {"hour": 19, "minute": 47, "second": 2}, "price": 5755.54113262},
{"time": {"hour": 19, "minute": 44, "second": 1}, "price": 5752.25730135},
{"time": {"hour": 19, "minute": 42, "second": 2}, "price": 5751.3632396},
{"time": {"hour": 19, "minute": 39, "second": 1}, "price": 5750.18689463},
{"time": {"hour": 19, "minute": 37, "second": 1}, "price": 5753.87256745},
{"time": {"hour": 19, "minute": 34, "second": 2}, "price": 5757.93643766},
{"time": {"hour": 19, "minute": 32, "second": 1}, "price": 5761.04430104},
{"time": {"hour": 19, "minute": 29, "second": 1}, "price": 5770.09403625},
{"time": {"hour": 19, "minute": 27, "second": 1}, "price": 5775.98612451},
{"time": {"hour": 19, "minute": 24, "second": 2}, "price": 5774.60449539},
{"time": {"hour": 19, "minute": 22, "second": 2}, "price": 5778.66604302},
{"time": {"hour": 19, "minute": 19, "second": 1}, "price": 5782.64256107},
{"time": {"hour": 19, "minute": 17, "second": 2}, "price": 5786.86555805},
{"time": {"hour": 19, "minute": 14, "second": 1}, "price": 5799.52218222},
{"time": {"hour": 19, "minute": 12, "second": 1}, "price": 5796.17781825},
{"time": {"hour": 19, "minute": 9, "second": 2}, "price": 5793.27017218},
{"time": {"hour": 19, "minute": 6, "second": 3}, "price": 5797.58822969},
{"time": {"hour": 19, "minute": 4, "second": 2}, "price": 5801.2585669},
{"time": {"hour": 19, "minute": 1, "second": 2}, "price": 5803.19223562},
{"time": {"hour": 18, "minute": 59, "second": 2}, "price": 5805.18866245},
{"time": {"hour": 18, "minute": 56, "second": 4}, "price": 5807.89543121},
{"time": {"hour": 18, "minute": 54, "second": 1}, "price": 5807.82225427},
{"time": {"hour": 18, "minute": 51, "second": 2}, "price": 5813.90680374},
{"time": {"hour": 18, "minute": 49, "second": 2}, "price": 5814.29749967},
{"time": {"hour": 18, "minute": 46, "second": 2}, "price": 5816.30080204},
{"time": {"hour": 18, "minute": 44, "second": 2}, "price": 5816.45006596},
{"time": {"hour": 18, "minute": 41, "second": 2}, "price": 5816.0446411},
{"time": {"hour": 18, "minute": 39, "second": 1}, "price": 5819.34189325},
{"time": {"hour": 18, "minute": 36, "second": 1}, "price": 5813.84879366},
{"time": {"hour": 18, "minute": 33, "second": 2}, "price": 5815.54101972},
{"time": {"hour": 18, "minute": 31, "second": 3}, "price": 5813.02891725},
{"time": {"hour": 18, "minute": 28, "second": 2}, "price": 5812.76546821},
{"time": {"hour": 18, "minute": 26, "second": 2}, "price": 5815.55750872},
{"time": {"hour": 18, "minute": 23, "second": 1}, "price": 5812.81341037},
{"time": {"hour": 18, "minute": 21, "second": 2}, "price": 5810.74383549},
{"time": {"hour": 18, "minute": 18, "second": 1}, "price": 5808.96494218},
{"time": {"hour": 18, "minute": 16, "second": 1}, "price": 5811.19822829},
{"time": {"hour": 18, "minute": 13, "second": 1}, "price": 5809.82990168},
{"time": {"hour": 18, "minute": 11, "second": 1}, "price": 5807.50578297},
{"time": {"hour": 18, "minute": 8, "second": 1}, "price": 5808.57331084},
{"time": {"hour": 18, "minute": 6, "second": 1}, "price": 5805.2133388},
{"time": {"hour": 18, "minute": 3, "second": 2}, "price": 5804.00472},
{"time": {"hour": 18, "minute": 1, "second": 1}, "price": 5805.14052586},
{"time": {"hour": 17, "minute": 58, "second": 2}, "price": 5808.25751775},
{"time": {"hour": 17, "minute": 56, "second": 2}, "price": 5808.56550326},
{"time": {"hour": 17, "minute": 53, "second": 1}, "price": 5815.38394936},
{"time": {"hour": 17, "minute": 50, "second": 2}, "price": 5815.74330636},
{"time": {"hour": 17, "minute": 48, "second": 1}, "price": 5816.18133717},
{"time": {"hour": 17, "minute": 45, "second": 2}, "price": 5820.11416277},
{"time": {"hour": 17, "minute": 43, "second": 2}, "price": 5816.48239552},
{"time": {"hour": 17, "minute": 40, "second": 2}, "price": 5817.11867032},
{"time": {"hour": 17, "minute": 38, "second": 2}, "price": 5812.07848755},
{"time": {"hour": 17, "minute": 35, "second": 2}, "price": 5813.28879502},
{"time": {"hour": 17, "minute": 32, "second": 3}, "price": 5810.5050564},
{"time": {"hour": 17, "minute": 30, "second": 2}, "price": 5811.5263845},
{"time": {"hour": 17, "minute": 27, "second": 1}, "price": 5811.68982157},
{"time": {"hour": 17, "minute": 25, "second": 1}, "price": 5809.91385772},
{"time": {"hour": 17, "minute": 22, "second": 1}, "price": 5809.16397684},
{"time": {"hour": 17, "minute": 20, "second": 1}, "price": 5804.76723349},
{"time": {"hour": 17, "minute": 17, "second": 2}, "price": 5801.40906458},
{"time": {"hour": 17, "minute": 15, "second": 2}, "price": 5801.24525172},
{"time": {"hour": 17, "minute": 12, "second": 1}, "price": 5809.53812701},
{"time": {"hour": 17, "minute": 10, "second": 1}, "price": 5806.49011545},
{"time": {"hour": 17, "minute": 7, "second": 1}, "price": 5827.72626285},
{"time": {"hour": 17, "minute": 5, "second": 1}, "price": 5830.34140515},
{"time": {"hour": 17, "minute": 2, "second": 2}, "price": 5836.83353233},
{"time": {"hour": 17, "minute": 0, "second": 1}, "price": 5849.55219166},
{"time": {"hour": 16, "minute": 57, "second": 1}, "price": 5853.08654937},
{"time": {"hour": 16, "minute": 55, "second": 1}, "price": 5852.34043746},
{"time": {"hour": 16, "minute": 52, "second": 2}, "price": 5857.74641815},
{"time": {"hour": 16, "minute": 49, "second": 3}, "price": 5853.6392097},
{"time": {"hour": 16, "minute": 47, "second": 1}, "price": 5850.91565685},
{"time": {"hour": 16, "minute": 44, "second": 2}, "price": 5850.51121803},
{"time": {"hour": 16, "minute": 42, "second": 2}, "price": 5848.51564176},
{"time": {"hour": 16, "minute": 39, "second": 2}, "price": 5848.54251228},
{"time": {"hour": 16, "minute": 37, "second": 2}, "price": 5850.34209964},
{"time": {"hour": 16, "minute": 34, "second": 1}, "price": 5852.47348924},
{"time": {"hour": 16, "minute": 32, "second": 1}, "price": 5848.91127215},
{"time": {"hour": 16, "minute": 29, "second": 2}, "price": 5847.92724762},
{"time": {"hour": 16, "minute": 27, "second": 2}, "price": 5848.03021155},
{"time": {"hour": 16, "minute": 24, "second": 1}, "price": 5841.95002938},
{"time": {"hour": 16, "minute": 22, "second": 1}, "price": 5841.41031229},
{"time": {"hour": 16, "minute": 19, "second": 2}, "price": 5838.44515278},
{"time": {"hour": 16, "minute": 16, "second": 2}, "price": 5836.36356207},
{"time": {"hour": 16, "minute": 14, "second": 2}, "price": 5830.63921288},
{"time": {"hour": 16, "minute": 11, "second": 1}, "price": 5829.19129845},
{"time": {"hour": 16, "minute": 9, "second": 1}, "price": 5829.70159632},
{"time": {"hour": 16, "minute": 6, "second": 1}, "price": 5830.33222543},
{"time": {"hour": 16, "minute": 4, "second": 1}, "price": 5831.2441438},
{"time": {"hour": 16, "minute": 1, "second": 1}, "price": 5834.37615865},
{"time": {"hour": 15, "minute": 59, "second": 3}, "price": 5834.97737919},
{"time": {"hour": 15, "minute": 56, "second": 1}, "price": 5834.21586373},
{"time": {"hour": 15, "minute": 54, "second": 2}, "price": 5835.69058689},
{"time": {"hour": 15, "minute": 51, "second": 1}, "price": 5831.90808401},
{"time": {"hour": 15, "minute": 48, "second": 5}, "price": 5831.08872457},
{"time": {"hour": 15, "minute": 46, "second": 2}, "price": 5829.1714003},
{"time": {"hour": 15, "minute": 43, "second": 2}, "price": 5829.52506796},
{"time": {"hour": 15, "minute": 41, "second": 2}, "price": 5830.51889009},
{"time": {"hour": 15, "minute": 38, "second": 2}, "price": 5829.72431136},
{"time": {"hour": 15, "minute": 36, "second": 1}, "price": 5825.75608486},
{"time": {"hour": 15, "minute": 33, "second": 1}, "price": 5819.80964069},
{"time": {"hour": 15, "minute": 31, "second": 1}, "price": 5819.33382791},
{"time": {"hour": 15, "minute": 28, "second": 2}, "price": 5818.70783171},
{"time": {"hour": 15, "minute": 26, "second": 2}, "price": 5817.71905213},
{"time": {"hour": 15, "minute": 23, "second": 1}, "price": 5812.09676517},
{"time": {"hour": 15, "minute": 21, "second": 2}, "price": 5813.21871929},
{"time": {"hour": 15, "minute": 18, "second": 2}, "price": 5811.76652262},
{"time": {"hour": 15, "minute": 16, "second": 2}, "price": 5807.89620874},
{"time": {"hour": 15, "minute": 13, "second": 1}, "price": 5801.25106235},
{"time": {"hour": 15, "minute": 10, "second": 2}, "price": 5799.79918558},
{"time": {"hour": 15, "minute": 8, "second": 1}, "price": 5800.17755908},
{"time": {"hour": 15, "minute": 5, "second": 1}, "price": 5799.79934669},
{"time": {"hour": 15, "minute": 3, "second": 2}, "price": 5806.81205764},
{"time": {"hour": 15, "minute": 0, "second": 1}, "price": 5809.84360705},
{"time": {"hour": 14, "minute": 58, "second": 2}, "price": 5812.33780705},
{"time": {"hour": 14, "minute": 55, "second": 2}, "price": 5812.10624041},
{"time": {"hour": 14, "minute": 53, "second": 2}, "price": 5814.96167233},
{"time": {"hour": 14, "minute": 50, "second": 2}, "price": 5817.12309119},
{"time": {"hour": 14, "minute": 48, "second": 2}, "price": 5820.2840067},
{"time": {"hour": 14, "minute": 45, "second": 1}, "price": 5817.45641276},
{"time": {"hour": 14, "minute": 43, "second": 2}, "price": 5817.01677263},
{"time": {"hour": 14, "minute": 40, "second": 1}, "price": 5812.1347092},
{"time": {"hour": 14, "minute": 37, "second": 2}, "price": 5809.23565586},
{"time": {"hour": 14, "minute": 35, "second": 2}, "price": 5804.39573285},
{"time": {"hour": 14, "minute": 32, "second": 1}, "price": 5800.88635366},
{"time": {"hour": 14, "minute": 30, "second": 1}, "price": 5794.98829185},
{"time": {"hour": 14, "minute": 27, "second": 2}, "price": 5796.11497125},
{"time": {"hour": 14, "minute": 25, "second": 1}, "price": 5795.79541859},
{"time": {"hour": 14, "minute": 22, "second": 2}, "price": 5798.16601769},
{"time": {"hour": 14, "minute": 20, "second": 2}, "price": 5794.86159435},
{"time": {"hour": 14, "minute": 17, "second": 6}, "price": 5795.27685114},
{"time": {"hour": 14, "minute": 15, "second": 2}, "price": 5790.50337199},
{"time": {"hour": 14, "minute": 12, "second": 2}, "price": 5787.39021928},
{"time": {"hour": 14, "minute": 9, "second": 1}, "price": 5790.7254505},
{"time": {"hour": 14, "minute": 7, "second": 1}, "price": 5791.52143777},
{"time": {"hour": 14, "minute": 4, "second": 1}, "price": 5796.91644394},
{"time": {"hour": 14, "minute": 2, "second": 1}, "price": 5804.16374345},
{"time": {"hour": 13, "minute": 59, "second": 1}, "price": 5803.7958853},
{"time": {"hour": 13, "minute": 57, "second": 1}, "price": 5803.61727595},
{"time": {"hour": 13, "minute": 54, "second": 2}, "price": 5804.38552922},
{"time": {"hour": 13, "minute": 52, "second": 1}, "price": 5799.57654941},
{"time": {"hour": 13, "minute": 49, "second": 1}, "price": 5798.26558942},
{"time": {"hour": 13, "minute": 47, "second": 1}, "price": 5790.55079767},
{"time": {"hour": 13, "minute": 44, "second": 2}, "price": 5785.72943658},
{"time": {"hour": 13, "minute": 42, "second": 1}, "price": 5779.011749},
{"time": {"hour": 13, "minute": 39, "second": 2}, "price": 5774.17822732},
{"time": {"hour": 13, "minute": 36, "second": 1}, "price": 5768.75727386},
{"time": {"hour": 13, "minute": 34, "second": 3}, "price": 5771.21589041},
{"time": {"hour": 13, "minute": 31, "second": 2}, "price": 5775.38651179},
{"time": {"hour": 13, "minute": 29, "second": 2}, "price": 5774.46896015},
{"time": {"hour": 13, "minute": 26, "second": 1}, "price": 5780.66992437},
{"time": {"hour": 13, "minute": 24, "second": 1}, "price": 5778.5567359},
{"time": {"hour": 13, "minute": 21, "second": 1}, "price": 5780.11042056},
{"time": {"hour": 13, "minute": 19, "second": 1}, "price": 5780.29150291},
{"time": {"hour": 13, "minute": 16, "second": 1}, "price": 5776.54472946},
{"time": {"hour": 13, "minute": 14, "second": 1}, "price": 5777.95396354},
{"time": {"hour": 13, "minute": 11, "second": 2}, "price": 5776.92025444},
{"time": {"hour": 13, "minute": 9, "second": 1}, "price": 5780.31373012},
{"time": {"hour": 13, "minute": 6, "second": 2}, "price": 5782.72329612},
{"time": {"hour": 13, "minute": 3, "second": 2}, "price": 5793.20127578},
{"time": {"hour": 13, "minute": 1, "second": 3}, "price": 5803.7101186},
{"time": {"hour": 12, "minute": 58, "second": 3}, "price": 5814.48388513},
{"time": {"hour": 12, "minute": 56, "second": 1}, "price": 5821.28866638},
{"time": {"hour": 12, "minute": 53, "second": 1}, "price": 5820.75273742},
{"time": {"hour": 12, "minute": 51, "second": 1}, "price": 5820.03655652},
{"time": {"hour": 12, "minute": 48, "second": 1}, "price": 5823.97580489},
{"time": {"hour": 12, "minute": 46, "second": 1}, "price": 5825.04573802},
{"time": {"hour": 12, "minute": 43, "second": 1}, "price": 5823.83308564},
{"time": {"hour": 12, "minute": 41, "second": 1}, "price": 5822.16215994},
{"time": {"hour": 12, "minute": 38, "second": 4}, "price": 5822.71159586},
{"time": {"hour": 12, "minute": 36, "second": 2}, "price": 5816.21854079},
{"time": {"hour": 12, "minute": 33, "second": 1}, "price": 5813.45597896},
{"time": {"hour": 12, "minute": 30, "second": 2}, "price": 5812.05580851},
{"time": {"hour": 12, "minute": 28, "second": 2}, "price": 5809.10106192},
{"time": {"hour": 12, "minute": 25, "second": 4}, "price": 5808.11690743},
{"time": {"hour": 12, "minute": 23, "second": 1}, "price": 5811.27548675},
{"time": {"hour": 12, "minute": 20, "second": 2}, "price": 5813.8508455},
{"time": {"hour": 12, "minute": 18, "second": 1}, "price": 5817.08400581},
{"time": {"hour": 12, "minute": 15, "second": 2}, "price": 5825.64829405},
{"time": {"hour": 12, "minute": 13, "second": 1}, "price": 5842.40379304},
{"time": {"hour": 12, "minute": 10, "second": 2}, "price": 5854.73979672},
{"time": {"hour": 12, "minute": 8, "second": 1}, "price": 5865.42194427},
{"time": {"hour": 12, "minute": 5, "second": 1}, "price": 5864.90226901},
{"time": {"hour": 12, "minute": 3, "second": 1}, "price": 5848.22029101},
{"time": {"hour": 12, "minute": 0, "second": 2}, "price": 5840.39331077},
{"time": {"hour": 11, "minute": 57, "second": 1}, "price": 5826.86115697},
{"time": {"hour": 11, "minute": 55, "second": 1}, "price": 5826.51568269},
{"time": {"hour": 11, "minute": 52, "second": 1}, "price": 5812.72780769},
{"time": {"hour": 11, "minute": 50, "second": 1}, "price": 5806.8797643},
{"time": {"hour": 11, "minute": 47, "second": 2}, "price": 5799.15637142},
{"time": {"hour": 11, "minute": 45, "second": 2}, "price": 5791.09457491},
{"time": {"hour": 11, "minute": 42, "second": 1}, "price": 5786.02258912},
{"time": {"hour": 11, "minute": 40, "second": 1}, "price": 5775.79669673},
{"time": {"hour": 11, "minute": 37, "second": 2}, "price": 5763.09740431},
{"time": {"hour": 11, "minute": 35, "second": 2}, "price": 5765.5355152},
{"time": {"hour": 11, "minute": 32, "second": 3}, "price": 5767.54734617},
{"time": {"hour": 11, "minute": 30, "second": 1}, "price": 5765.45878116},
{"time": {"hour": 11, "minute": 27, "second": 2}, "price": 5761.79929889},
{"time": {"hour": 11, "minute": 25, "second": 2}, "price": 5737.12361354},
{"time": {"hour": 11, "minute": 22, "second": 2}, "price": 5741.8905908},
{"time": {"hour": 11, "minute": 19, "second": 1}, "price": 5754.85705213},
{"time": {"hour": 11, "minute": 17, "second": 1}, "price": 5757.50360113},
{"time": {"hour": 11, "minute": 14, "second": 2}, "price": 5758.22168119},
{"time": {"hour": 11, "minute": 12, "second": 1}, "price": 5764.743168},
{"time": {"hour": 11, "minute": 9, "second": 2}, "price": 5765.43918881},
{"time": {"hour": 11, "minute": 7, "second": 2}, "price": 5762.419351},
{"time": {"hour": 11, "minute": 4, "second": 1}, "price": 5762.8552971},
{"time": {"hour": 11, "minute": 2, "second": 1}, "price": 5751.03951435},
{"time": {"hour": 10, "minute": 59, "second": 1}, "price": 5751.05488765},
{"time": {"hour": 10, "minute": 57, "second": 1}, "price": 5717.26180638},
{"time": {"hour": 10, "minute": 54, "second": 2}, "price": 5709.96297764},
{"time": {"hour": 10, "minute": 52, "second": 2}, "price": 5710.54578784},
{"time": {"hour": 10, "minute": 49, "second": 2}, "price": 5705.31126637},
{"time": {"hour": 10, "minute": 46, "second": 1}, "price": 5699.47924646},
{"time": {"hour": 10, "minute": 44, "second": 1}, "price": 5680.98228331},
{"time": {"hour": 10, "minute": 41, "second": 2}, "price": 5676.94114069},
{"time": {"hour": 10, "minute": 39, "second": 1}, "price": 5676.86197278},
{"time": {"hour": 10, "minute": 36, "second": 2}, "price": 5678.60135068},
{"time": {"hour": 10, "minute": 34, "second": 2}, "price": 5677.32266123},
{"time": {"hour": 10, "minute": 31, "second": 1}, "price": 5678.90007743},
{"time": {"hour": 10, "minute": 29, "second": 1}, "price": 5678.74643481},
{"time": {"hour": 10, "minute": 26, "second": 1}, "price": 5677.19392539},
{"time": {"hour": 10, "minute": 24, "second": 1}, "price": 5676.17497524},
{"time": {"hour": 10, "minute": 21, "second": 3}, "price": 5677.61814045},
{"time": {"hour": 10, "minute": 19, "second": 1}, "price": 5673.41894021},
{"time": {"hour": 10, "minute": 16, "second": 1}, "price": 5671.95838963},
{"time": {"hour": 10, "minute": 14, "second": 1}, "price": 5680.32025117},
{"time": {"hour": 10, "minute": 11, "second": 1}, "price": 5683.12651587},
{"time": {"hour": 10, "minute": 8, "second": 2}, "price": 5688.35200638},
{"time": {"hour": 10, "minute": 6, "second": 3}, "price": 5687.52758791},
{"time": {"hour": 10, "minute": 3, "second": 2}, "price": 5689.31719801},
{"time": {"hour": 10, "minute": 1, "second": 1}, "price": 5688.83740239},
{"time": {"hour": 9, "minute": 58, "second": 2}, "price": 5680.98685533},
{"time": {"hour": 9, "minute": 56, "second": 2}, "price": 5682.69801885},
{"time": {"hour": 9, "minute": 53, "second": 2}, "price": 5674.06430977},
{"time": {"hour": 9, "minute": 51, "second": 3}, "price": 5667.41238349},
{"time": {"hour": 9, "minute": 48, "second": 2}, "price": 5658.53576549},
{"time": {"hour": 9, "minute": 46, "second": 2}, "price": 5651.69686063},
{"time": {"hour": 9, "minute": 43, "second": 2}, "price": 5649.71390909},
{"time": {"hour": 9, "minute": 40, "second": 1}, "price": 5648.95469159},
{"time": {"hour": 9, "minute": 38, "second": 3}, "price": 5647.53623849},
{"time": {"hour": 9, "minute": 35, "second": 1}, "price": 5650.25199933},
{"time": {"hour": 9, "minute": 33, "second": 2}, "price": 5648.22045796},
{"time": {"hour": 9, "minute": 30, "second": 1}, "price": 5649.05272865},
{"time": {"hour": 9, "minute": 28, "second": 1}, "price": 5647.86189393},
{"time": {"hour": 9, "minute": 25, "second": 2}, "price": 5646.06879959},
{"time": {"hour": 9, "minute": 23, "second": 6}, "price": 5643.55081244},
{"time": {"hour": 9, "minute": 20, "second": 1}, "price": 5640.09199922},
{"time": {"hour": 9, "minute": 18, "second": 1}, "price": 5636.86878862},
{"time": {"hour": 9, "minute": 15, "second": 2}, "price": 5640.21844214},
{"time": {"hour": 9, "minute": 13, "second": 1}, "price": 5636.78784739},
{"time": {"hour": 9, "minute": 10, "second": 1}, "price": 5631.31236908},
{"time": {"hour": 9, "minute": 8, "second": 1}, "price": 5628.92574782},
{"time": {"hour": 9, "minute": 5, "second": 1}, "price": 5629.88326445},
{"time": {"hour": 9, "minute": 2, "second": 2}, "price": 5627.57703055},
{"time": {"hour": 9, "minute": 0, "second": 2}, "price": 5629.96755233},
{"time": {"hour": 8, "minute": 57, "second": 1}, "price": 5629.39354995},
{"time": {"hour": 8, "minute": 55, "second": 2}, "price": 5632.89748157},
{"time": {"hour": 8, "minute": 52, "second": 1}, "price": 5634.84891663},
{"time": {"hour": 8, "minute": 50, "second": 2}, "price": 5638.00610175},
{"time": {"hour": 8, "minute": 47, "second": 1}, "price": 5650.35324969},
{"time": {"hour": 8, "minute": 45, "second": 1}, "price": 5651.86836982},
{"time": {"hour": 8, "minute": 42, "second": 1}, "price": 5645.77449981},
{"time": {"hour": 8, "minute": 40, "second": 1}, "price": 5642.16882436},
{"time": {"hour": 8, "minute": 37, "second": 2}, "price": 5637.67750783},
{"time": {"hour": 8, "minute": 35, "second": 2}, "price": 5633.32757198},
{"time": {"hour": 8, "minute": 32, "second": 2}, "price": 5627.34654443},
{"time": {"hour": 8, "minute": 29, "second": 1}, "price": 5617.10265325},
{"time": {"hour": 8, "minute": 27, "second": 2}, "price": 5611.60424703},
{"time": {"hour": 8, "minute": 24, "second": 1}, "price": 5604.19884767},
{"time": {"hour": 8, "minute": 22, "second": 1}, "price": 5601.85429663},
{"time": {"hour": 8, "minute": 19, "second": 1}, "price": 5597.99825897},
{"time": {"hour": 8, "minute": 17, "second": 1}, "price": 5599.98169946},
{"time": {"hour": 8, "minute": 14, "second": 2}, "price": 5601.17699162},
{"time": {"hour": 8, "minute": 12, "second": 2}, "price": 5600.03061722},
{"time": {"hour": 8, "minute": 9, "second": 2}, "price": 5600.4481653},
{"time": {"hour": 8, "minute": 6, "second": 3}, "price": 5601.60444046},
{"time": {"hour": 8, "minute": 4, "second": 1}, "price": 5599.32553571},
{"time": {"hour": 8, "minute": 1, "second": 2}, "price": 5600.21849188},
{"time": {"hour": 7, "minute": 59, "second": 1}, "price": 5595.102728},
{"time": {"hour": 7, "minute": 56, "second": 4}, "price": 5591.30090563},
{"time": {"hour": 7, "minute": 54, "second": 2}, "price": 5591.08436221},
{"time": {"hour": 7, "minute": 51, "second": 2}, "price": 5592.95118751},
{"time": {"hour": 7, "minute": 49, "second": 1}, "price": 5590.28906402},
{"time": {"hour": 7, "minute": 46, "second": 2}, "price": 5590.69547435},
{"time": {"hour": 7, "minute": 44, "second": 2}, "price": 5591.22009953},
{"time": {"hour": 7, "minute": 41, "second": 2}, "price": 5590.42800398},
{"time": {"hour": 7, "minute": 38, "second": 2}, "price": 5591.16219128},
{"time": {"hour": 7, "minute": 36, "second": 2}, "price": 5590.04348519},
{"time": {"hour": 7, "minute": 33, "second": 1}, "price": 5588.05345384},
{"time": {"hour": 7, "minute": 31, "second": 1}, "price": 5586.88909963},
{"time": {"hour": 7, "minute": 28, "second": 1}, "price": 5585.92687022},
{"time": {"hour": 7, "minute": 26, "second": 2}, "price": 5585.83916007},
{"time": {"hour": 7, "minute": 23, "second": 3}, "price": 5584.67605989},
{"time": {"hour": 7, "minute": 21, "second": 1}, "price": 5585.09173747},
{"time": {"hour": 7, "minute": 18, "second": 2}, "price": 5586.81652418},
{"time": {"hour": 7, "minute": 16, "second": 2}, "price": 5586.10642319},
{"time": {"hour": 7, "minute": 13, "second": 1}, "price": 5587.5006141},
{"time": {"hour": 7, "minute": 11, "second": 1}, "price": 5589.19339774},
{"time": {"hour": 7, "minute": 8, "second": 1}, "price": 5592.75782233},
{"time": {"hour": 7, "minute": 5, "second": 2}, "price": 5594.00887295},
{"time": {"hour": 7, "minute": 3, "second": 2}, "price": 5593.53074094},
{"time": {"hour": 7, "minute": 0, "second": 1}, "price": 5592.8664923},
{"time": {"hour": 6, "minute": 58, "second": 2}, "price": 5590.29053123},
{"time": {"hour": 6, "minute": 55, "second": 1}, "price": 5592.5961429},
{"time": {"hour": 6, "minute": 53, "second": 1}, "price": 5594.39376958},
{"time": {"hour": 6, "minute": 50, "second": 1}, "price": 5590.42858932},
{"time": {"hour": 6, "minute": 48, "second": 2}, "price": 5588.67650027},
{"time": {"hour": 6, "minute": 45, "second": 1}, "price": 5584.57935553},
{"time": {"hour": 6, "minute": 43, "second": 2}, "price": 5583.11749075},
{"time": {"hour": 6, "minute": 40, "second": 2}, "price": 5580.35558667},
{"time": {"hour": 6, "minute": 37, "second": 1}, "price": 5576.43071226},
{"time": {"hour": 6, "minute": 35, "second": 1}, "price": 5578.44369981},
{"time": {"hour": 6, "minute": 32, "second": 2}, "price": 5577.90578446},
{"time": {"hour": 6, "minute": 30, "second": 2}, "price": 5576.55748034},
{"time": {"hour": 6, "minute": 27, "second": 2}, "price": 5577.26495922},
{"time": {"hour": 6, "minute": 25, "second": 1}, "price": 5576.20795827},
{"time": {"hour": 6, "minute": 22, "second": 1}, "price": 5575.26358219},
{"time": {"hour": 6, "minute": 20, "second": 1}, "price": 5572.42184469},
{"time": {"hour": 6, "minute": 17, "second": 3}, "price": 5573.45357273},
{"time": {"hour": 6, "minute": 15, "second": 1}, "price": 5573.83315735},
{"time": {"hour": 6, "minute": 12, "second": 2}, "price": 5573.35787399},
{"time": {"hour": 6, "minute": 10, "second": 1}, "price": 5576.70041178},
{"time": {"hour": 6, "minute": 7, "second": 2}, "price": 5579.33714358},
{"time": {"hour": 6, "minute": 4, "second": 1}, "price": 5578.8592679},
{"time": {"hour": 6, "minute": 2, "second": 1}, "price": 5580.51381042},
{"time": {"hour": 5, "minute": 59, "second": 2}, "price": 5580.41238809},
{"time": {"hour": 5, "minute": 57, "second": 1}, "price": 5582.98839437},
{"time": {"hour": 5, "minute": 54, "second": 2}, "price": 5578.32807104},
{"time": {"hour": 5, "minute": 52, "second": 2}, "price": 5577.12568651},
{"time": {"hour": 5, "minute": 49, "second": 2}, "price": 5574.05101553},
{"time": {"hour": 5, "minute": 47, "second": 2}, "price": 5572.49029139},
{"time": {"hour": 5, "minute": 44, "second": 1}, "price": 5571.47379249},
{"time": {"hour": 5, "minute": 42, "second": 2}, "price": 5570.8937948},
{"time": {"hour": 5, "minute": 39, "second": 1}, "price": 5569.29913128},
{"time": {"hour": 5, "minute": 36, "second": 1}, "price": 5569.37075386},
{"time": {"hour": 5, "minute": 34, "second": 1}, "price": 5570.28052547},
{"time": {"hour": 5, "minute": 31, "second": 1}, "price": 5571.07377846},
{"time": {"hour": 5, "minute": 29, "second": 1}, "price": 5570.62281758},
{"time": {"hour": 5, "minute": 26, "second": 2}, "price": 5571.7156455},
{"time": {"hour": 5, "minute": 24, "second": 1}, "price": 5572.3696259},
{"time": {"hour": 5, "minute": 21, "second": 1}, "price": 5572.13500159},
{"time": {"hour": 5, "minute": 19, "second": 1}, "price": 5576.68196817},
{"time": {"hour": 5, "minute": 16, "second": 1}, "price": 5575.55673613},
{"time": {"hour": 5, "minute": 14, "second": 1}, "price": 5578.97014064},
{"time": {"hour": 5, "minute": 11, "second": 3}, "price": 5577.60522405},
{"time": {"hour": 5, "minute": 9, "second": 1}, "price": 5579.00600285},
{"time": {"hour": 5, "minute": 6, "second": 2}, "price": 5579.81448037},
{"time": {"hour": 5, "minute": 3, "second": 2}, "price": 5571.97465857},
{"time": {"hour": 5, "minute": 1, "second": 2}, "price": 5576.05349569},
{"time": {"hour": 4, "minute": 58, "second": 2}, "price": 5565.23610966},
{"time": {"hour": 4, "minute": 56, "second": 2}, "price": 5568.58340412},
{"time": {"hour": 4, "minute": 53, "second": 1}, "price": 5564.89687309},
{"time": {"hour": 4, "minute": 51, "second": 2}, "price": 5562.1428745},
{"time": {"hour": 4, "minute": 48, "second": 3}, "price": 5560.87216654},
{"time": {"hour": 4, "minute": 46, "second": 2}, "price": 5558.97317483},
{"time": {"hour": 4, "minute": 43, "second": 1}, "price": 5558.56080141},
{"time": {"hour": 4, "minute": 41, "second": 1}, "price": 5557.62937332},
{"time": {"hour": 4, "minute": 38, "second": 2}, "price": 5558.91276234},
{"time": {"hour": 4, "minute": 35, "second": 2}, "price": 5556.79901497},
{"time": {"hour": 4, "minute": 33, "second": 4}, "price": 5554.91238363},
{"time": {"hour": 4, "minute": 30, "second": 1}, "price": 5552.74829239},
{"time": {"hour": 4, "minute": 28, "second": 1}, "price": 5554.16939855},
{"time": {"hour": 4, "minute": 25, "second": 1}, "price": 5550.55594053},
{"time": {"hour": 4, "minute": 23, "second": 1}, "price": 5551.70927895},
{"time": {"hour": 4, "minute": 20, "second": 1}, "price": 5554.44696977},
{"time": {"hour": 4, "minute": 18, "second": 1}, "price": 5555.40516293},
{"time": {"hour": 4, "minute": 15, "second": 1}, "price": 5552.78431439},
{"time": {"hour": 4, "minute": 13, "second": 1}, "price": 5550.85658089},
{"time": {"hour": 4, "minute": 10, "second": 4}, "price": 5549.0228939},
{"time": {"hour": 4, "minute": 7, "second": 2}, "price": 5548.67806374},
{"time": {"hour": 4, "minute": 5, "second": 2}, "price": 5550.21655185},
{"time": {"hour": 4, "minute": 2, "second": 1}, "price": 5552.48946396},
{"time": {"hour": 4, "minute": 0, "second": 3}, "price": 5555.74075993},
{"time": {"hour": 3, "minute": 57, "second": 1}, "price": 5554.00173702},
{"time": {"hour": 3, "minute": 55, "second": 2}, "price": 5549.0803302},
{"time": {"hour": 3, "minute": 52, "second": 2}, "price": 5547.90837611},
{"time": {"hour": 3, "minute": 50, "second": 1}, "price": 5542.86111953},
{"time": {"hour": 3, "minute": 47, "second": 2}, "price": 5537.10742102},
{"time": {"hour": 3, "minute": 45, "second": 2}, "price": 5541.20657572},
{"time": {"hour": 3, "minute": 42, "second": 1}, "price": 5537.36866164},
{"time": {"hour": 3, "minute": 39, "second": 1}, "price": 5539.92688002},
{"time": {"hour": 3, "minute": 37, "second": 1}, "price": 5541.10191941},
{"time": {"hour": 3, "minute": 34, "second": 2}, "price": 5537.68641167},
{"time": {"hour": 3, "minute": 32, "second": 2}, "price": 5538.60135531},
{"time": {"hour": 3, "minute": 29, "second": 1}, "price": 5540.58552991},
{"time": {"hour": 3, "minute": 27, "second": 1}, "price": 5539.06799359},
{"time": {"hour": 3, "minute": 24, "second": 1}, "price": 5541.89026609},
{"time": {"hour": 3, "minute": 22, "second": 1}, "price": 5538.12597278},
{"time": {"hour": 3, "minute": 19, "second": 1}, "price": 5535.81600437},
{"time": {"hour": 3, "minute": 17, "second": 2}, "price": 5533.64949961},
{"time": {"hour": 3, "minute": 14, "second": 1}, "price": 5529.84304215},
{"time": {"hour": 3, "minute": 11, "second": 1}, "price": 5528.75564528},
{"time": {"hour": 3, "minute": 9, "second": 1}, "price": 5526.28822399},
{"time": {"hour": 3, "minute": 6, "second": 2}, "price": 5524.03827407},
{"time": {"hour": 3, "minute": 4, "second": 1}, "price": 5522.56562528},
{"time": {"hour": 3, "minute": 1, "second": 3}, "price": 5519.91845111},
{"time": {"hour": 2, "minute": 59, "second": 1}, "price": 5512.85385297},
{"time": {"hour": 2, "minute": 56, "second": 2}, "price": 5514.24163284},
{"time": {"hour": 2, "minute": 54, "second": 2}, "price": 5514.73241819},
{"time": {"hour": 2, "minute": 51, "second": 2}, "price": 5511.72024692},
{"time": {"hour": 2, "minute": 49, "second": 2}, "price": 5512.60533918},
{"time": {"hour": 2, "minute": 46, "second": 1}, "price": 5508.45251811},
{"time": {"hour": 2, "minute": 43, "second": 2}, "price": 5509.37713669},
{"time": {"hour": 2, "minute": 41, "second": 1}, "price": 5504.2776541},
{"time": {"hour": 2, "minute": 38, "second": 1}, "price": 5502.35731675},
{"time": {"hour": 2, "minute": 36, "second": 1}, "price": 5497.15383568},
{"time": {"hour": 2, "minute": 33, "second": 3}, "price": 5490.2018629},
{"time": {"hour": 2, "minute": 31, "second": 2}, "price": 5494.13485701},
{"time": {"hour": 2, "minute": 28, "second": 3}, "price": 5493.63637566},
{"time": {"hour": 2, "minute": 25, "second": 2}, "price": 5492.28511495},
{"time": {"hour": 2, "minute": 23, "second": 2}, "price": 5490.91261091},
{"time": {"hour": 2, "minute": 20, "second": 2}, "price": 5491.18915511},
{"time": {"hour": 2, "minute": 18, "second": 2}, "price": 5491.15571586},
{"time": {"hour": 2, "minute": 15, "second": 1}, "price": 5495.26918521},
{"time": {"hour": 2, "minute": 13, "second": 2}, "price": 5500.36782682},
{"time": {"hour": 2, "minute": 10, "second": 2}, "price": 5503.6232171},
{"time": {"hour": 2, "minute": 8, "second": 2}, "price": 5503.15373097},
{"time": {"hour": 2, "minute": 5, "second": 2}, "price": 5505.28367176},
{"time": {"hour": 2, "minute": 3, "second": 1}, "price": 5505.07022937},
{"time": {"hour": 2, "minute": 0, "second": 3}, "price": 5503.51558243},
{"time": {"hour": 1, "minute": 58, "second": 1}, "price": 5505.25916482},
{"time": {"hour": 1, "minute": 55, "second": 1}, "price": 5506.29835475},
{"time": {"hour": 1, "minute": 52, "second": 2}, "price": 5506.47026771},
{"time": {"hour": 1, "minute": 50, "second": 1}, "price": 5504.67094786},
{"time": {"hour": 1, "minute": 47, "second": 2}, "price": 5506.19960353},
{"time": {"hour": 1, "minute": 45, "second": 2}, "price": 5507.95239632},
{"time": {"hour": 1, "minute": 42, "second": 1}, "price": 5508.31957222},
{"time": {"hour": 1, "minute": 40, "second": 1}, "price": 5505.60706183},
{"time": {"hour": 1, "minute": 37, "second": 1}, "price": 5506.87850455},
{"time": {"hour": 1, "minute": 35, "second": 1}, "price": 5506.60704607},
{"time": {"hour": 1, "minute": 32, "second": 4}, "price": 5507.11065996},
{"time": {"hour": 1, "minute": 30, "second": 1}, "price": 5507.49041774},
{"time": {"hour": 1, "minute": 27, "second": 2}, "price": 5506.18895834},
{"time": {"hour": 1, "minute": 25, "second": 2}, "price": 5505.07953537},
{"time": {"hour": 1, "minute": 22, "second": 1}, "price": 5504.01703832},
{"time": {"hour": 1, "minute": 20, "second": 1}, "price": 5504.43863119},
{"time": {"hour": 1, "minute": 17, "second": 1}, "price": 5505.46893612},
{"time": {"hour": 1, "minute": 14, "second": 2}, "price": 5503.14757331},
{"time": {"hour": 1, "minute": 12, "second": 2}, "price": 5503.62064643},
{"time": {"hour": 1, "minute": 9, "second": 3}, "price": 5501.01687901},
{"time": {"hour": 1, "minute": 7, "second": 1}, "price": 5504.66325535},
{"time": {"hour": 1, "minute": 4, "second": 1}, "price": 5502.97907071},
{"time": {"hour": 1, "minute": 2, "second": 1}, "price": 5503.55092884},
{"time": {"hour": 0, "minute": 59, "second": 2}, "price": 5503.45099759},
{"time": {"hour": 0, "minute": 57, "second": 1}, "price": 5505.55449044},
{"time": {"hour": 0, "minute": 54, "second": 2}, "price": 5505.68697332},
{"time": {"hour": 0, "minute": 52, "second": 2}, "price": 5504.32219456},
{"time": {"hour": 0, "minute": 49, "second": 1}, "price": 5504.97254548},
{"time": {"hour": 0, "minute": 47, "second": 5}, "price": 5505.32955619},
{"time": {"hour": 0, "minute": 44, "second": 1}, "price": 5506.60782277},
{"time": {"hour": 0, "minute": 41, "second": 2}, "price": 5507.254156},
{"time": {"hour": 0, "minute": 39, "second": 2}, "price": 5508.08966323},
{"time": {"hour": 0, "minute": 36, "second": 1}, "price": 5509.21232376},
{"time": {"hour": 0, "minute": 34, "second": 1}, "price": 5505.29445729},
{"time": {"hour": 0, "minute": 31, "second": 6}, "price": 5504.64931787},
{"time": {"hour": 0, "minute": 29, "second": 2}, "price": 5504.6329871},
{"time": {"hour": 0, "minute": 26, "second": 1}, "price": 5506.43443987},
{"time": {"hour": 0, "minute": 24, "second": 1}, "price": 5504.44567214},
{"time": {"hour": 0, "minute": 21, "second": 1}, "price": 5501.35095946},
{"time": {"hour": 0, "minute": 19, "second": 1}, "price": 5502.61635894},
{"time": {"hour": 0, "minute": 16, "second": 2}, "price": 5502.68590669},
{"time": {"hour": 0, "minute": 14, "second": 2}, "price": 5501.23870389},
{"time": {"hour": 0, "minute": 11, "second": 1}, "price": 5508.13692974},
{"time": {"hour": 0, "minute": 8, "second": 2}, "price": 5506.90563342},
{"time": {"hour": 0, "minute": 6, "second": 3}, "price": 5507.21382832},
{"time": {"hour": 0, "minute": 3, "second": 1}, "price": 5510.62743332},
{"time": {"hour": 0, "minute": 1, "second": 1}, "price": 5512.55592779},
{"time": {"hour": 0, "minute": 0, "second": 2}, "price": 5511.85211799}
]
